grimp-3.12.dist-info/METADATA
grimp-3.12.dist-info/WHEEL
grimp-3.12.dist-info/licenses/AUTHORS.rst
grimp-3.12.dist-info/licenses/LICENSE
grimp.libs/libgcc_s-98a1ef30.so.1
grimp/__init__.py
grimp/_rustgrimp.cpython-311-x86_64-linux-musl.so
grimp/adaptors/__init__.py
grimp/adaptors/caching.py
grimp/adaptors/filesystem.py
grimp/adaptors/graph.py
grimp/adaptors/modulefinder.py
grimp/adaptors/packagefinder.py
grimp/adaptors/timing.py
grimp/application/__init__.py
grimp/application/config.py
grimp/application/ports/__init__.py
grimp/application/ports/caching.py
grimp/application/ports/filesystem.py
grimp/application/ports/graph.py
grimp/application/ports/modulefinder.py
grimp/application/ports/packagefinder.py
grimp/application/ports/timing.py
grimp/application/scanning.py
grimp/application/usecases.py
grimp/domain/__init__.py
grimp/domain/analysis.py
grimp/domain/valueobjects.py
grimp/exceptions.py
grimp/main.py
grimp/py.typed
grimp-3.12.dist-info/RECORD
