Metadata-Version: 2.4
Name: grimp
Version: 3.12
Classifier: Development Status :: 5 - Production/Stable
Classifier: Intended Audience :: Developers
Classifier: License :: OSI Approved :: BSD License
Classifier: Operating System :: Unix
Classifier: Operating System :: POSIX
Classifier: Operating System :: Microsoft :: Windows
Classifier: Programming Language :: Python
Classifier: Programming Language :: Python :: 3.9
Classifier: Programming Language :: Python :: 3.10
Classifier: Programming Language :: Python :: 3.11
Classifier: Programming Language :: Python :: 3.12
Classifier: Programming Language :: Python :: 3.13
Classifier: Programming Language :: Python :: 3.14
Classifier: Programming Language :: Python :: Implementation :: CPython
Classifier: Programming Language :: Rust
Classifier: Topic :: Utilities
Requires-Dist: typing-extensions>=3.10.0.0
License-File: LICENSE
License-File: AUTHORS.rst
Summary: Builds a queryable graph of the imports within one or more Python packages.
Author-email: David Seddon <david@seddonym.me>
License: BSD 2-Clause License
Requires-Python: >=3.9
Project-URL: Documentation, https://grimp.readthedocs.io/
Project-URL: Source-code, https://github.com/seddonym/grimp/
